[
  {
    "id": "book_551",
    "legacyId": 551,
    "title": "АРХЕТИПЫ ВНУТРЕННЕЙ СЕМЬИ",
    "author": null,
    "shortDescription": "Кэролайн Хэнстке, Брайен и Тереза Эммануэл ГрейПсихология эпохи Водолея Случались ли у вас проблемы во взаимоотношениях со своей второй половиной, с боссом или с одноклассниками? Понимаете ли вы, поче...",
    "longDescription": "Кэролайн Хэнстке, Брайен и Тереза Эммануэл ГрейПсихология эпохи Водолея Случались ли у вас проблемы во взаимоотношениях со своей второй половиной, с боссом или с одноклассниками? Понимаете ли вы, почему делаете то, что делаете? Знаете ли свои сильные и слабые стороны? Эта книга поможет найти ответы на подобные вопросы, понять, на чем вы «спотыкаетесь» в жизни, из каких побуждений действуют окружающие вас люди. Она научит вас строить прочные и надежные отношения, полные любви и взаимопонимания со всеми, кого вы встречаете на жизненном пути. Предложенный подход к пониманию и разрешению психологических проблем нов и оригинален, но при этом опирается на известные издревле духовные истины. Твёрдый переплет. 145/211мм. 310 страниц.",
    "price": 520,
    "wholesalePrice1": null,
    "wholesalePrice2": null,
    "weight": null,
    "sku": null,
    "inStock": true,
    "dimensions": null,
    "pages": null,
    "publisher": null,
    "isbn": null,
    "publishYear": null,
    "images": {
      "thumbnail": "/images/products/book/thumbnails/551.webp",
      "large": null
    },
    "category": "book",
    "subcategory": "psychology",
    "originalImagePath": "/shopimg/551s.jpg"
  }
]